oryx/__init__.py
oryx/bijectors/__init__.py
oryx/core/__init__.py
oryx/core/interpreters/__init__.py
oryx/core/interpreters/harvest.py
oryx/core/interpreters/harvest_test.py
oryx/core/interpreters/inverse/__init__.py
oryx/core/interpreters/inverse/bijector_extensions.py
oryx/core/interpreters/inverse/bijector_extensions_test.py
oryx/core/interpreters/inverse/core.py
oryx/core/interpreters/inverse/custom_inverse.py
oryx/core/interpreters/inverse/custom_inverse_test.py
oryx/core/interpreters/inverse/inverse_test.py
oryx/core/interpreters/inverse/rules.py
oryx/core/interpreters/inverse/slice.py
oryx/core/interpreters/inverse/slice_test.py
oryx/core/interpreters/log_prob.py
oryx/core/interpreters/log_prob_test.py
oryx/core/interpreters/propagate.py
oryx/core/interpreters/propagate_test.py
oryx/core/kwargs_util.py
oryx/core/kwargs_util_test.py
oryx/core/ppl/__init__.py
oryx/core/ppl/effect_handler.py
oryx/core/ppl/effect_handler_test.py
oryx/core/ppl/plate_util.py
oryx/core/ppl/transformations.py
oryx/core/ppl/transformations_test.py
oryx/core/primitive.py
oryx/core/primitive_test.py
oryx/core/pytree.py
oryx/core/serialize.py
oryx/core/serialize_test.py
oryx/core/state/__init__.py
oryx/core/state/api.py
oryx/core/state/function.py
oryx/core/state/function_test.py
oryx/core/state/module.py
oryx/core/state/registrations.py
oryx/core/state/registrations_test.py
oryx/core/trace_util.py
oryx/distributions/__init__.py
oryx/distributions/distribution_extensions.py
oryx/distributions/distribution_extensions_test.py
oryx/examples/notebooks/a_tour_of_oryx.ipynb
oryx/examples/notebooks/probabilistic_programming.ipynb
oryx/experimental/__init__.py
oryx/experimental/autoconj/addn.py
oryx/experimental/autoconj/addn_test.py
oryx/experimental/autoconj/canonicalize.py
oryx/experimental/autoconj/canonicalize_test.py
oryx/experimental/autoconj/einsum.py
oryx/experimental/autoconj/einsum_test.py
oryx/experimental/matching/__init__.py
oryx/experimental/matching/jax_rewrite.py
oryx-0.2.9.dist-info/LICENSE
oryx-0.2.9.dist-info/METADATA
oryx-0.2.9.dist-info/WHEEL
oryx-0.2.9.dist-info/RECORD
