Metadata-Version: 2.1
Name: oryx
Version: 0.2.9
Summary: Probabilistic programming and deep learning in JAX
License: Apache 2.0
Author: Google LLC
Requires-Python: >=3.10,<4.0
Classifier: License :: Other/Proprietary License
Classifier: Programming Language :: Python :: 3
Classifier: Programming Language :: Python :: 3.10
Classifier: Programming Language :: Python :: 3.11
Classifier: Programming Language :: Python :: 3.12
Requires-Dist: jax (>=0.4.36)
Requires-Dist: tensorflow-probability (>=0.19.0)
